Metadata-Version: 1.1
Name: ipython-futhark
Version: 1.1.2
Summary: Futhark language embedding into IPython
Home-page: https://github.com/titouanc/ipython-futhark
Author: Titouan Christophe
Author-email: moiandme@gmail.com
License: MIT
Keywords: futhark ipython gpu
Platform: UNKNOWN
Classifier: Development Status :: 3 - Alpha
Classifier: Environment :: Console
Classifier: License :: OSI Approved :: MIT License
Classifier: Programming Language :: Python :: 3
Classifier: Programming Language :: Python :: 2
Classifier: Framework :: IPython
Classifier: Framework :: Jupyter
